openbao_settings/__init__.py
openbao_settings/client.py
openbao_settings/models.py
openbao_settings/py.typed
openbao_settings/source.py
openbao_pydantic_settings_adapter-1.0.4.dist-info/METADATA
openbao_pydantic_settings_adapter-1.0.4.dist-info/WHEEL
openbao_pydantic_settings_adapter-1.0.4.dist-info/licenses/LICENSE
openbao_pydantic_settings_adapter-1.0.4.dist-info/RECORD
