Metadata-Version: 2.4
Name: openbao-pydantic-settings-adapter
Version: 1.0.4
Summary: OpenBao/Vault secrets source for pydantic-settings with AppRole authentication
Project-URL: Homepage, https://github.com/itstandart/openbao-pydantic-settings-adapter
Project-URL: Repository, https://github.com/itstandart/openbao-pydantic-settings-adapter
Project-URL: Documentation, https://github.com/itstandart/openbao-pydantic-settings-adapter#readme
Project-URL: Issues, https://github.com/itstandart/openbao-pydantic-settings-adapter/issues
Author-email: IT Standart <aitistandart@gmail.com>
License-Expression: LicenseRef-PolyForm-Noncommercial-1.0.0
License-File: LICENSE
Keywords: approle,configuration,openbao,pydantic,pydantic-settings,secrets,vault
Classifier: Development Status :: 4 - Beta
Classifier: Framework :: Pydantic :: 2
Classifier: Intended Audience :: Developers
Classifier: License :: Other/Proprietary License
Classifier: Operating System :: OS Independent
Classifier: Programming Language :: Python :: 3
Classifier: Programming Language :: Python :: 3.11
Classifier: Programming Language :: Python :: 3.12
Classifier: Programming Language :: Python :: 3.13
Classifier: Programming Language :: Python :: 3.14
Classifier: Topic :: Security
Classifier: Topic :: Software Development :: Libraries :: Python Modules
Classifier: Typing :: Typed
Requires-Python: >=3.11
Requires-Dist: httpx>=0.28.0
Requires-Dist: pydantic-settings>=2.0.0
Requires-Dist: pydantic>=2.10.0
Requires-Dist: python-dotenv>=1.0.0
Provides-Extra: dev
Requires-Dist: mypy>=1.13.0; extra == 'dev'
Requires-Dist: ruff>=0.8.0; extra == 'dev'
